mseep_alibaba_cloud_ops_mcp_server-0.9.8.dist-info/licenses/LICENSE
src/__init__.py
src/alibaba_cloud_ops_mcp_server/__init__.py
src/alibaba_cloud_ops_mcp_server/config.py
src/alibaba_cloud_ops_mcp_server/server.py
src/alibaba_cloud_ops_mcp_server/alibabacloud/__init__.py
src/alibaba_cloud_ops_mcp_server/alibabacloud/api_meta_client.py
src/alibaba_cloud_ops_mcp_server/alibabacloud/exception.py
src/alibaba_cloud_ops_mcp_server/alibabacloud/utils.py
src/alibaba_cloud_ops_mcp_server/alibabacloud/static/__init__.py
src/alibaba_cloud_ops_mcp_server/tools/__init__.py
src/alibaba_cloud_ops_mcp_server/tools/api_tools.py
src/alibaba_cloud_ops_mcp_server/tools/cms_tools.py
src/alibaba_cloud_ops_mcp_server/tools/common_api_tools.py
src/alibaba_cloud_ops_mcp_server/tools/oos_tools.py
src/alibaba_cloud_ops_mcp_server/tools/oss_tools.py
mseep_alibaba_cloud_ops_mcp_server-0.9.8.dist-info/METADATA
mseep_alibaba_cloud_ops_mcp_server-0.9.8.dist-info/WHEEL
mseep_alibaba_cloud_ops_mcp_server-0.9.8.dist-info/top_level.txt
mseep_alibaba_cloud_ops_mcp_server-0.9.8.dist-info/RECORD
